zlshenpi/__init__.py
zlshenpi/util/__init__.py
zlshenpi/util/cfg_db
zlshenpi/util/conf.py
zlshenpi/util/data.py
zlshenpi/util/etl.py
zlshenpi/util/fake_useragent.py
zlshenpi/zlshenpi/__init__.py
zlshenpi/zlshenpi/anhuisheng.py
zlshenpi/zlshenpi/beijingshi.py
zlshenpi/zlshenpi/default_path.txt
zlshenpi/zlshenpi/fujiansheng.py
zlshenpi/zlshenpi/gansusheng.py
zlshenpi/zlshenpi/guangdongsheng.py
zlshenpi/zlshenpi/hebeisheng.py
zlshenpi/zlshenpi/heilongjiangsheng.py
zlshenpi/zlshenpi/henansheng.py
zlshenpi/zlshenpi/hubeisheng.py
zlshenpi/zlshenpi/hunansheng.py
zlshenpi/zlshenpi/jiangxisheng.py
zlshenpi/zlshenpi/jilinsheng.py
zlshenpi/zlshenpi/neimenggusheng.py
zlshenpi/zlshenpi/ningxiasheng.py
zlshenpi/zlshenpi/qinghaisheng.py
zlshenpi/zlshenpi/shanxisheng.py
zlshenpi/zlshenpi/shanxisheng1.py
zlshenpi/zlshenpi/sichuansheng.py
zlshenpi/zlshenpi/task.py
zlshenpi/zlshenpi/xiamenshi.py
zlshenpi/zlshenpi/xinjiangsheng.py
zlshenpi/zlshenpi/yunnansheng.py
zlshenpi/zlshenpi/zhejiangsheng.py
zlshenpi-1.1.30.dist-info/METADATA
zlshenpi-1.1.30.dist-info/WHEEL
zlshenpi-1.1.30.dist-info/top_level.txt
zlshenpi-1.1.30.dist-info/RECORD
